{
    "jn": "jn :slight_smile:",
    "cs": "henlo <:peepolove:747845162071490742>",
    "je \u010derstv\u00e1": "nen\u00ed \u010derstv\u00e1 <:Reee:747845163279319180>",
    "nen\u00ed \u010derstv\u00e1": "je \u010derstv\u00e1 <:Reee:747845163279319180>",
    "eo": "eo",
    "gn": "gn <:pac:752499683682811935>",
    "Gn": "gn <:pac:752499683682811935>",
    "gm": "gm <:pac:752499683682811935>",
    "Gm": "gm <:pac:752499683682811935>",
    "F": "F <:peepoCry:687038268365340738>",
    "valec": "prost\u011b_v\u00e1lec",
    "<:pepegun:734751832781488148>": "<:monkaH:687431847302791212>",
    "tom\u00e1\u0161": "Prost\u011b k\u00e1mo lejta vo vejn\u011b",
    "Rada": "Celib\u00e1t je m\u016fj nejlep\u0161\u00ed kamar\u00e1d",
    "Zuzana": "BATMAN",
    "Vojta": "retard",
    "Formes": "\"dokadim ten mek\u00e1\u010d a du\"",
    "nanana": "He's gonna fly",
    "Monnte": "splesnety jogurt",
    "monnte": "operacny boh Ing. Peter Softwarovy Inzinier matematik.",
    "rada": "Tom\u00e1\u0161 2.0",
    "danka": "<@!105045328738164736>  <@!463706956369100800>",
    "Marek": "vie\u0161 mi kupi\u0165 peniaze",
    "ilbinek": "ka\u017ed\u00fd m\u00e1 svoji p\u0159edur\u010denou d\u00edru",
    "dan": "no to nenene"
  }